foundry_rest_api_relay_client/__init__.py
foundry_rest_api_relay_client/api/__init__.py
foundry_rest_api_relay_client/api/scenes/__init__.py
foundry_rest_api_relay_client/api/scenes/activate_scene_scenes_id_activate_get.py
foundry_rest_api_relay_client/api/scenes/create_scene_scenes_id_post.py
foundry_rest_api_relay_client/api/scenes/delete_scene_scenes_id_delete.py
foundry_rest_api_relay_client/api/scenes/get_active_scene_scenes_utils_active_get.py
foundry_rest_api_relay_client/api/scenes/get_scene_scenes_id_get.py
foundry_rest_api_relay_client/api/scenes/get_scenes_scenes_get.py
foundry_rest_api_relay_client/api/scenes/update_scene_scenes_id_patch.py
foundry_rest_api_relay_client/api/utility/__init__.py
foundry_rest_api_relay_client/api/utility/ping_ping_get.py
foundry_rest_api_relay_client/client.py
foundry_rest_api_relay_client/errors.py
foundry_rest_api_relay_client/models/__init__.py
foundry_rest_api_relay_client/models/foundry_scene.py
foundry_rest_api_relay_client/models/foundry_scene_ownership_type_0.py
foundry_rest_api_relay_client/models/http_validation_error.py
foundry_rest_api_relay_client/models/texture_data.py
foundry_rest_api_relay_client/models/tile_data.py
foundry_rest_api_relay_client/models/validation_error.py
foundry_rest_api_relay_client/models/wall_data.py
foundry_rest_api_relay_client/py.typed
foundry_rest_api_relay_client/types.py
foundry_rest_api_relay_client-0.1.0.dist-info/METADATA
foundry_rest_api_relay_client-0.1.0.dist-info/WHEEL
foundry_rest_api_relay_client-0.1.0.dist-info/RECORD
